gurgle/__init__.py
gurgle/base.py
gurgle/sp_gurgle.py
gurgle/terminal.py
gurgle/util.py
gurgle-0.0.11.dist-info/LICENSE
gurgle-0.0.11.dist-info/METADATA
gurgle-0.0.11.dist-info/WHEEL
gurgle-0.0.11.dist-info/entry_points.txt
gurgle-0.0.11.dist-info/top_level.txt
gurgle-0.0.11.dist-info/RECORD
