Metadata-Version: 2.1
Name: gurgle
Version: 0.0.11
Summary: Wrappers to extend ML processing components (perform online/mini-batch learning - track residues - store data - track drift etc.)
Home-page: https://github.com/otosense/gurgle
Author: OtoSense
License: apache-2.0
Platform: any
Requires-Dist: creek
Requires-Dist: lined
Requires-Dist: taped
Requires-Dist: slang
